LAB_Sumador/Circuitos/Sumador-restador/Suma_resta.v
/*
 * Generated by Digital. Don't modify this file!
 * Any changes will be lost if this file is regenerated.
 */
/*
 * Generated by Digital. Don't modify this file!
 * Any changes will be lost if this file is regenerated.
 */

module asig (
  input O,
  input A,
  input B,
  input CBi,
  output CBo,
  output S
);
  wire s0;
  assign s0 = ~ A;
  assign CBo = ((A & CBi & ~ O) | (A & B & ~ O) | (s0 & CBi & O) | (s0 & B & O) | (B & CBi));
  assign S = ((s0 & ~ B & CBi) | (s0 & B & ~ CBi) | (A & ~ B & ~ CBi) | (A & B & CBi));
endmodule


module Suma_resta (
  input a1,
  input b1,
  input a0,
  input b0,
  input a3,
  input b3,
  input a2,
  input b2,
  input Op,
  output s1,
  output s0,
  output s3,
  output s2,
  output s4
);
  wire s5;
  wire s6;
  wire s7;
  // asig
  asig asig_i0 (
    .O( Op ),
    .A( a0 ),
    .B( b0 ),
    .CBi( 1'b0 ),
    .CBo( s5 ),
    .S( s0 )
  );
  // asig
  asig asig_i1 (
    .O( Op ),
    .A( a1 ),
    .B( b1 ),
    .CBi( s5 ),
    .CBo( s6 ),
    .S( s1 )
  );
  // asig
  asig asig_i2 (
    .O( Op ),
    .A( a2 ),
    .B( b2 ),
    .CBi( s6 ),
    .CBo( s7 ),
    .S( s2 )
  );
  // asig
  asig asig_i3 (
    .O( Op ),
    .A( a3 ),
    .B( b3 ),
    .CBi( s7 ),
    .CBo( s4 ),
    .S( s3 )
  );
endmodule

LAB_Sumador/Circuitos/Sumador-restador/suma_resta_tb.v
module testbech;

  // STIMULUS
  // reg a = 0, b = 0;
  // initial
  // begin
  //   # 17 a = 1, b = 1;
  //   # 11 a = 1, b = 0;
  //   # 29 a = 1, b = 1;
  //   # 11 a = 1, b = 0;
  //   # 100 $finish(); // [stop(), $finish()]
  // end
  reg input_o;
  integer e;
  reg [3:0] input_a;
  integer i;
  reg [3:0] input_b;
  integer o;
  initial
  begin
  for (e=0; e<2; e=e+1)
  begin         
		input_o = e;
		for (i=0; i<16; i=i+1)
		begin         
			input_a = i;
			for (o=0; o<16; o=o+1)
			begin         
			  input_b = o;
			  #1;
			end
		end
	end
  end

  // CLOCK STIMULUS
  // Make a regular pulsing clock.
  // reg clk = 0;
  // always #5 clk = !clk;

  /* // RESULT FOR DEVICE/DESIGN UNDER TEST */
  wire [4:0] outs;
  // DEVICE/DESIGN UNDER TEST
  Suma_resta dut (
	.Op(input_o),
	.a3(input_a[3]), .a2(input_a[2]), .a1(input_a[1]), .a0(input_a[0]), 
	.b3(input_b[3]), .b2(input_b[2]), .b1(input_b[1]), .b0(input_b[0]), 
	.s4(outs[4]), .s3(outs[3]), .s2(outs[2]), .s1(outs[1]), .s0(outs[0])
  );

  /* // MONITOR */
  // initial
  //   $monitor("Time: %t, a = %d, b = %d => out = %d",
  //     $time, a, b, value);

  // WAVES IN VCD TO OPEN IN GTKWAVE
  initial
  begin
    $dumpfile("top.vcd");
    $dumpvars(0, testbech);
  end


endmodule

LAB_Sumador/Circuitos/Sumador-restador/top.vcd
$date
	Wed Oct 11 23:53:57 2023
$end
$version
	Icarus Verilog
$end
$timescale
	1s
$end
$scope module testbech $end
$var wire 5 ! outs [4:0] $end
$var reg 4 " input_a [3:0] $end
$var reg 4 # input_b [3:0] $end
$var reg 1 $ input_o $end
$var integer 32 % e [31:0] $end
$var integer 32 & i [31:0] $end
$var integer 32 ' o [31:0] $end
$scope module dut $end
$var wire 1 $ Op $end
$var wire 1 ( a0 $end
$var wire 1 ) a1 $end
$var wire 1 * a2 $end
$var wire 1 + a3 $end
$var wire 1 , b0 $end
$var wire 1 - b1 $end
$var wire 1 . b2 $end
$var wire 1 / b3 $end
$var wire 1 0 s7 $end
$var wire 1 1 s6 $end
$var wire 1 2 s5 $end
$var wire 1 3 s4 $end
$var wire 1 4 s3 $end
$var wire 1 5 s2 $end
$var wire 1 6 s1 $end
$var wire 1 7 s0 $end
$scope module asig_i0 $end
$var wire 1 ( A $end
$var wire 1 , B $end
$var wire 1 8 CBi $end
$var wire 1 2 CBo $end
$var wire 1 $ O $end
$var wire 1 7 S $end
$var wire 1 9 s0 $end
$upscope $end
$scope module asig_i1 $end
$var wire 1 ) A $end
$var wire 1 - B $end
$var wire 1 2 CBi $end
$var wire 1 1 CBo $end
$var wire 1 $ O $end
$var wire 1 6 S $end
$var wire 1 : s0 $end
$upscope $end
$scope module asig_i2 $end
$var wire 1 * A $end
$var wire 1 . B $end
$var wire 1 1 CBi $end
$var wire 1 0 CBo $end
$var wire 1 $ O $end
$var wire 1 5 S $end
$var wire 1 ; s0 $end
$upscope $end
$scope module asig_i3 $end
$var wire 1 + A $end
$var wire 1 / B $end
$var wire 1 0 CBi $end
$var wire 1 3 CBo $end
$var wire 1 $ O $end
$var wire 1 4 S $end
$var wire 1 < s0 $end
$upscope $end
$upscope $end
$upscope $end
$enddefinitions $end
#0
$dumpvars
1<
1;
1:
19
08
07
06
05
04
03
02
01
00
0/
0.
0-
0,
0+
0*
0)
0(
b0 '
b0 &
b0 %
0$
b0 #
b0 "
b0 !
$end
#1
b1 !
17
1,
b1 #
b1 '
#2
16
b10 !
07
1-
0,
b10 #
b10 '
#3
b11 !
17
1,
b11 #
b11 '
#4
06
07
b100 !
15
0-
0,
1.
b100 #
b100 '
#5
b101 !
17
1,
b101 #
b101 '
#6
16
b110 !
07
1-
0,
b110 #
b110 '
#7
b111 !
17
1,
b111 #
b111 '
#8
06
07
14
b1000 !
05
0-
0,
1/
0.
b1000 #
b1000 '
#9
b1001 !
17
1,
b1001 #
b1001 '
#10
16
b1010 !
07
1-
0,
b1010 #
b1010 '
#11
b1011 !
17
1,
b1011 #
b1011 '
#12
06
07
b1100 !
15
0-
0,
1.
b1100 #
b1100 '
#13
b1101 !
17
1,
b1101 #
b1101 '
#14
16
b1110 !
07
1-
0,
b1110 #
b1110 '
#15
b1111 !
17
1,
b1111 #
b1111 '
#16
06
04
b1 !
05
09
0-
0,
0/
0.
1(
b0 #
b1 "
b1 &
b0 '
#17
16
12
b10 !
07
1,
b1 #
b1 '
#18
05
16
02
b11 !
17
01
1-
0,
b10 #
b10 '
#19
15
06
11
12
b100 !
07
1,
b11 #
b11 '
#20
06
02
04
15
b101 !
17
01
00
0-
0,
1.
b100 #
b100 '
#21
16
12
b110 !
07
1,
b101 #
b101 '
#22
04
15
16
02
b111 !
17
00
01
1-
0,
b110 #
b110 '
#23
14
05
06
10
11
12
b1000 !
07
1,
b111 #
b111 '
#24
06
02
17
01
b1001 !
03
00
0-
0,
1/
0.
b1000 #
b1000 '
#25
16
12
b1010 !
07
1,
b1001 #
b1001 '
#26
05
16
02
b1011 !
17
01
1-
0,
b1010 #
b1010 '
#27
15
06
11
12
b1100 !
07
1,
b1011 #
b1011 '
#28
14
06
02
15
17
b1101 !
03
01
00
0-
0,
1.
b1100 #
b1100 '
#29
16
12
b1110 !
07
1,
b1101 #
b1101 '
#30
14
15
03
16
02
b1111 !
17
00
01
1-
0,
b1110 #
b1110 '
#31
04
05
13
06
10
11
12
b10000 !
07
1,
b1111 #
b1111 '
#32
05
16
02
01
b10 !
03
00
0:
19
0-
0,
0/
0.
1)
0(
b0 #
b10 "
b10 &
b0 '
#33
b11 !
17
1,
b1 #
b1 '
#34
15
11
06
b100 !
07
1-
0,
b10 #
b10 '
#35
b101 !
17
1,
b11 #
b11 '
#36
01
04
15
16
b110 !
07
00
0-
0,
1.
b100 #
b100 '
#37
b111 !
17
1,
b101 #
b101 '
#38
14
05
10
11
06
b1000 !
07
1-
0,
b110 #
b110 '
#39
b1001 !
17
1,
b111 #
b111 '
#40
01
05
16
07
b1010 !
03
00
0-
0,
1/
0.
b1000 #
b1000 '
#41
b1011 !
17
1,
b1001 #
b1001 '
#42
15
11
06
b1100 !
07
1-
0,
b1010 #
b1010 '
#43
b1101 !
17
1,
b1011 #
b1011 '
#44
14
01
15
16
07
b1110 !
03
00
0-
0,
1.
b1100 #
b1100 '
#45
b1111 !
17
1,
b1101 #
b1101 '
#46
04
05
13
10
11
06
b10000 !
07
1-
0,
b1110 #
b1110 '
#47
b10001 !
17
1,
b1111 #
b1111 '
#48
01
05
16
b11 !
03
00
09
0-
0,
0/
0.
1(
b0 #
b11 "
b11 &
b0 '
#49
15
11
06
12
b100 !
07
1,
b1 #
b1 '
#50
02
17
b101 !
06
1-
0,
b10 #
b10 '
#51
16
12
b110 !
07
1,
b11 #
b11 '
#52
01
02
04
15
17
b111 !
16
00
0-
0,
1.
b100 #
b100 '
#53
14
05
10
11
06
12
b1000 !
07
1,
b101 #
b101 '
#54
02
17
b1001 !
06
1-
0,
b110 #
b110 '
#55
16
12
b1010 !
07
1,
b111 #
b111 '
#56
01
02
05
17
16
b1011 !
03
00
0-
0,
1/
0.
b1000 #
b1000 '
#57
15
11
06
12
b1100 !
07
1,
b1001 #
b1001 '
#58
02
17
b1101 !
06
1-
0,
b1010 #
b1010 '
#59
16
12
b1110 !
07
1,
b1011 #
b1011 '
#60
01
14
02
15
17
03
b1111 !
16
00
0-
0,
1.
b1100 #
b1100 '
#61
04
05
13
10
11
06
12
b10000 !
07
1,
b1101 #
b1101 '
#62
02
17
b10001 !
06
1-
0,
b1110 #
b1110 '
#63
16
12
b10010 !
07
1,
b1111 #
b1111 '
#64
15
04
01
02
06
b100 !
03
00
1:
19
0;
0-
0,
0/
0.
0)
0(
1*
b0 #
b100 "
b100 &
b0 '
#65
b101 !
17
1,
b1 #
b1 '
#66
16
b110 !
07
1-
0,
b10 #
b10 '
#67
b111 !
17
1,
b11 #
b11 '
#68
14
10
06
07
b1000 !
05
0-
0,
1.
b100 #
b100 '
#69
b1001 !
17
1,
b101 #
b101 '
#70
16
b1010 !
07
1-
0,
b110 #
b110 '
#71
b1011 !
17
1,
b111 #
b111 '
#72
14
00
06
07
15
b1100 !
03
0-
0,
1/
0.
b1000 #
b1000 '
#73
b1101 !
17
1,
b1001 #
b1001 '
#74
16
b1110 !
07
1-
0,
b1010 #
b1010 '
#75
b1111 !
17
1,
b1011 #
b1011 '
#76
04
13
10
06
07
b10000 !
05
0-
0,
1.
b1100 #
b1100 '
#77
b10001 !
17
1,
b1101 #
b1101 '
#78
16
b10010 !
07
1-
0,
b1110 #
b1110 '
#79
b10011 !
17
1,
b1111 #
b1111 '
#80
04
00
06
15
b101 !
03
09
0-
0,
0/
0.
1(
b0 #
b101 "
b101 &
b0 '
#81
16
12
b110 !
07
1,
b1 #
b1 '
#82
04
00
15
16
02
b111 !
17
01
1-
0,
b10 #
b10 '
#83
14
10
05
06
11
12
b1000 !
07
1,
b11 #
b11 '
#84
06
02
17
b1001 !
05
01
0-
0,
1.
b100 #
b100 '
#85
16
12
b1010 !
07
1,
b101 #
b101 '
#86
16
02
17
b1011 !
05
01
1-
0,
b110 #
b110 '
#87
06
15
11
12
b1100 !
07
1,
b111 #
b111 '
#88
00
06
02
14
17
15
01
b1101 !
03
0-
0,
1/
0.
b1000 #
b1000 '
#89
16
12
b1110 !
07
1,
b1001 #
b1001 '
#90
14
03
00
15
16
02
b1111 !
17
01
1-
0,
b1010 #
b1010 '
#91
04
13
10
05
06
11
12
b10000 !
07
1,
b1011 #
b1011 '
#92
06
02
17
b10001 !
05
01
0-
0,
1.
b1100 #
b1100 '
#93
16
12
b10010 !
07
1,
b1101 #
b1101 '
#94
16
02
17
b10011 !
05
01
1-
0,
b1110 #
b1110 '
#95
06
15
11
12
b10100 !
07
1,
b1111 #
b1111 '
#96
16
00
04
02
15
01
b110 !
03
0:
19
0-
0,
0/
0.
1)
0(
b0 #
b110 "
b110 &
b0 '
#97
b111 !
17
1,
b1 #
b1 '
#98
14
10
05
11
06
b1000 !
07
1-
0,
b10 #
b10 '
#99
b1001 !
17
1,
b11 #
b11 '
#100
01
16
07
b1010 !
05
0-
0,
1.
b100 #
b100 '
#101
b1011 !
17
1,
b101 #
b101 '
#102
15
11
06
b1100 !
07
1-
0,
b110 #
b110 '
#103
b1101 !
17
1,
b111 #
b111 '
#104
00
01
14
16
07
15
b1110 !
03
0-
0,
1/
0.
b1000 #
b1000 '
#105
b1111 !
17
1,
b1001 #
b1001 '
#106
04
13
10
05
11
06
b10000 !
07
1-
0,
b1010 #
b1010 '
#107
b10001 !
17
1,
b1011 #
b1011 '
#108
01
16
07
b10010 !
05
0-
0,
1.
b1100 #
b1100 '
#109
b10011 !
17
1,
b1101 #
b1101 '
#110
15
11
06
b10100 !
07
1-
0,
b1110 #
b1110 '
#111
b10101 !
17
1,
b1111 #
b1111 '
#112
00
01
04
16
15
b111 !
03
09
0-
0,
0/
0.
1(
b0 #
b111 "
b111 &
b0 '
#113
14
10
05
11
06
12
b1000 !
07
1,
b1 #
b1 '
#114
02
17
b1001 !
06
1-
0,
b10 #
b10 '
#115
16
12
b1010 !
07
1,
b11 #
b11 '
#116
01
02
17
16
b1011 !
05
0-
0,
1.
b100 #
b100 '
#117
15
11
06
12
b1100 !
07
1,
b101 #
b101 '
#118
02
17
b1101 !
06
1-
0,
b110 #
b110 '
#119
16
12
b1110 !
07
1,
b111 #
b111 '
#120
00
01
02
14
17
16
15
b1111 !
03
0-
0,
1/
0.
b1000 #
b1000 '
#121
04
13
10
05
11
06
12
b10000 !
07
1,
b1001 #
b1001 '
#122
02
17
b10001 !
06
1-
0,
b1010 #
b1010 '
#123
16
12
b10010 !
07
1,
b1011 #
b1011 '
#124
01
02
17
16
b10011 !
05
0-
0,
1.
b1100 #
b1100 '
#125
15
11
06
12
b10100 !
07
1,
b1101 #
b1101 '
#126
02
17
b10101 !
06
1-
0,
b1110 #
b1110 '
#127
16
12
b10110 !
07
1,
b1111 #
b1111 '
#128
14
01
02
00
06
05
b1000 !
03
1:
19
0<
1;
0-
0,
0/
0.
0)
0(
1+
0*
b0 #
b1000 "
b1000 &
b0 '
#129
b1001 !
17
1,
b1 #
b1 '
#130
16
b1010 !
07
1-
0,
b10 #
b10 '
#131
b1011 !
17
1,
b11 #
b11 '
#132
06
07
b1100 !
15
0-
0,
1.
b100 #
b100 '
#133
b1101 !
17
1,
b101 #
b101 '
#134
16
b1110 !
07
1-
0,
b110 #
b110 '
#135
b1111 !
17
1,
b111 #
b111 '
#136
13
06
07
04
b10000 !
05
0-
0,
1/
0.
b1000 #
b1000 '
#137
b10001 !
17
1,
b1001 #
b1001 '
#138
16
b10010 !
07
1-
0,
b1010 #
b1010 '
#139
b10011 !
17
1,
b1011 #
b1011 '
#140
06
07
b10100 !
15
0-
0,
1.
b1100 #
b1100 '
#141
b10101 !
17
1,
b1101 #
b1101 '
#142
16
b10110 !
07
1-
0,
b1110 #
b1110 '
#143
b10111 !
17
1,
b1111 #
b1111 '
#144
03
06
14
b1001 !
05
09
0-
0,
0/
0.
1(
b0 #
b1001 "
b1001 &
b0 '
#145
16
12
b1010 !
07
1,
b1 #
b1 '
#146
05
16
02
b1011 !
17
01
1-
0,
b10 #
b10 '
#147
15
06
11
12
b1100 !
07
1,
b11 #
b11 '
#148
03
06
02
14
15
b1101 !
17
01
00
0-
0,
1.
b100 #
b100 '
#149
16
12
b1110 !
07
1,
b101 #
b101 '
#150
03
14
15
16
02
b1111 !
17
00
01
1-
0,
b110 #
b110 '
#151
13
04
05
06
10
11
12
b10000 !
07
1,
b111 #
b111 '
#152
06
02
b10001 !
17
01
00
0-
0,
1/
0.
b1000 #
b1000 '
#153
16
12
b10010 !
07
1,
b1001 #
b1001 '
#154
05
16
02
b10011 !
17
01
1-
0,
b1010 #
b1010 '
#155
15
06
11
12
b10100 !
07
1,
b1011 #
b1011 '
#156
06
02
15
17
b10101 !
04
01
00
0-
0,
1.
b1100 #
b1100 '
#157
16
12
b10110 !
07
1,
b1101 #
b1101 '
#158
15
04
16
02
b10111 !
17
00
01
1-
0,
b1110 #
b1110 '
#159
05
14
06
10
11
12
b11000 !
07
1,
b1111 #
b1111 '
#160
05
16
03
02
b1010 !
14
01
00
0:
19
0-
0,
0/
0.
1)
0(
b0 #
b1010 "
b1010 &
b0 '
#161
b1011 !
17
1,
b1 #
b1 '
#162
15
11
06
b1100 !
07
1-
0,
b10 #
b10 '
#163
b1101 !
17
1,
b11 #
b11 '
#164
03
01
14
15
16
b1110 !
07
00
0-
0,
1.
b100 #
b100 '
#165
b1111 !
17
1,
b101 #
b101 '
#166
13
04
05
10
11
06
b10000 !
07
1-
0,
b110 #
b110 '
#167
b10001 !
17
1,
b111 #
b111 '
#168
01
05
16
b10010 !
07
00
0-
0,
1/
0.
b1000 #
b1000 '
#169
b10011 !
17
1,
b1001 #
b1001 '
#170
15
11
06
b10100 !
07
1-
0,
b1010 #
b1010 '
#171
b10101 !
17
1,
b1011 #
b1011 '
#172
01
15
16
07
b10110 !
04
00
0-
0,
1.
b1100 #
b1100 '
#173
b10111 !
17
1,
b1101 #
b1101 '
#174
05
14
10
11
06
b11000 !
07
1-
0,
b1110 #
b1110 '
#175
b11001 !
17
1,
b1111 #
b1111 '
#176
03
01
05
16
b1011 !
14
00
09
0-
0,
0/
0.
1(
b0 #
b1011 "
b1011 &
b0 '
#177
15
11
06
12
b1100 !
07
1,
b1 #
b1 '
#178
02
17
b1101 !
06
1-
0,
b10 #
b10 '
#179
16
12
b1110 !
07
1,
b11 #
b11 '
#180
01
03
02
14
15
17
b1111 !
16
00
0-
0,
1.
b100 #
b100 '
#181
13
04
05
10
11
06
12
b10000 !
07
1,
b101 #
b101 '
#182
02
17
b10001 !
06
1-
0,
b110 #
b110 '
#183
16
12
b10010 !
07
1,
b111 #
b111 '
#184
01
02
05
17
b10011 !
16
00
0-
0,
1/
0.
b1000 #
b1000 '
#185
15
11
06
12
b10100 !
07
1,
b1001 #
b1001 '
#186
02
17
b10101 !
06
1-
0,
b1010 #
b1010 '
#187
16
12
b10110 !
07
1,
b1011 #
b1011 '
#188
01
02
15
17
04
b10111 !
16
00
0-
0,
1.
b1100 #
b1100 '
#189
05
14
10
11
06
12
b11000 !
07
1,
b1101 #
b1101 '
#190
02
17
b11001 !
06
1-
0,
b1110 #
b1110 '
#191
16
12
b11010 !
07
1,
b1111 #
b1111 '
#192
15
03
01
02
14
b1100 !
06
00
1:
19
0;
0-
0,
0/
0.
0)
0(
1*
b0 #
b1100 "
b1100 &
b0 '
#193
b1101 !
17
1,
b1 #
b1 '
#194
16
b1110 !
07
1-
0,
b10 #
b10 '
#195
b1111 !
17
1,
b11 #
b11 '
#196
13
04
10
06
07
b10000 !
05
0-
0,
1.
b100 #
b100 '
#197
b10001 !
17
1,
b101 #
b101 '
#198
16
b10010 !
07
1-
0,
b110 #
b110 '
#199
b10011 !
17
1,
b111 #
b111 '
#200
00
06
07
15
b10100 !
04
0-
0,
1/
0.
b1000 #
b1000 '
#201
b10101 !
17
1,
b1001 #
b1001 '
#202
16
b10110 !
07
1-
0,
b1010 #
b1010 '
#203
b10111 !
17
1,
b1011 #
b1011 '
#204
14
10
06
07
b11000 !
05
0-
0,
1.
b1100 #
b1100 '
#205
b11001 !
17
1,
b1101 #
b1101 '
#206
16
b11010 !
07
1-
0,
b1110 #
b1110 '
#207
b11011 !
17
1,
b1111 #
b1111 '
#208
03
00
06
15
b1101 !
14
09
0-
0,
0/
0.
1(
b0 #
b1101 "
b1101 &
b0 '
#209
16
12
b1110 !
07
1,
b1 #
b1 '
#210
03
14
00
15
16
02
b1111 !
17
01
1-
0,
b10 #
b10 '
#211
13
04
10
05
06
11
12
b10000 !
07
1,
b11 #
b11 '
#212
06
02
17
b10001 !
05
01
0-
0,
1.
b100 #
b100 '
#213
16
12
b10010 !
07
1,
b101 #
b101 '
#214
16
02
17
b10011 !
05
01
1-
0,
b110 #
b110 '
#215
06
15
11
12
b10100 !
07
1,
b111 #
b111 '
#216
00
06
02
17
04
b10101 !
15
01
0-
0,
1/
0.
b1000 #
b1000 '
#217
16
12
b10110 !
07
1,
b1001 #
b1001 '
#218
04
00
15
16
02
b10111 !
17
01
1-
0,
b1010 #
b1010 '
#219
14
10
05
06
11
12
b11000 !
07
1,
b1011 #
b1011 '
#220
06
02
17
b11001 !
05
01
0-
0,
1.
b1100 #
b1100 '
#221
16
12
b11010 !
07
1,
b1101 #
b1101 '
#222
16
02
17
b11011 !
05
01
1-
0,
b1110 #
b1110 '
#223
06
15
11
12
b11100 !
07
1,
b1111 #
b1111 '
#224
03
16
00
02
14
b1110 !
15
01
0:
19
0-
0,
0/
0.
1)
0(
b0 #
b1110 "
b1110 &
b0 '
#225
b1111 !
17
1,
b1 #
b1 '
#226
13
04
10
05
11
06
b10000 !
07
1-
0,
b10 #
b10 '
#227
b10001 !
17
1,
b11 #
b11 '
#228
01
16
07
b10010 !
05
0-
0,
1.
b100 #
b100 '
#229
b10011 !
17
1,
b101 #
b101 '
#230
15
11
06
b10100 !
07
1-
0,
b110 #
b110 '
#231
b10101 !
17
1,
b111 #
b111 '
#232
00
01
16
07
04
b10110 !
15
0-
0,
1/
0.
b1000 #
b1000 '
#233
b10111 !
17
1,
b1001 #
b1001 '
#234
14
10
05
11
06
b11000 !
07
1-
0,
b1010 #
b1010 '
#235
b11001 !
17
1,
b1011 #
b1011 '
#236
01
16
07
b11010 !
05
0-
0,
1.
b1100 #
b1100 '
#237
b11011 !
17
1,
b1101 #
b1101 '
#238
15
11
06
b11100 !
07
1-
0,
b1110 #
b1110 '
#239
b11101 !
17
1,
b1111 #
b1111 '
#240
03
00
01
16
14
b1111 !
15
09
0-
0,
0/
0.
1(
b0 #
b1111 "
b1111 &
b0 '
#241
13
04
10
05
11
06
12
b10000 !
07
1,
b1 #
b1 '
#242
02
17
b10001 !
06
1-
0,
b10 #
b10 '
#243
16
12
b10010 !
07
1,
b11 #
b11 '
#244
01
02
17
16
b10011 !
05
0-
0,
1.
b100 #
b100 '
#245
15
11
06
12
b10100 !
07
1,
b101 #
b101 '
#246
02
17
b10101 !
06
1-
0,
b110 #
b110 '
#247
16
12
b10110 !
07
1,
b111 #
b111 '
#248
00
01
02
17
16
04
b10111 !
15
0-
0,
1/
0.
b1000 #
b1000 '
#249
14
10
05
11
06
12
b11000 !
07
1,
b1001 #
b1001 '
#250
02
17
b11001 !
06
1-
0,
b1010 #
b1010 '
#251
16
12
b11010 !
07
1,
b1011 #
b1011 '
#252
01
02
17
16
b11011 !
05
0-
0,
1.
b1100 #
b1100 '
#253
15
11
06
12
b11100 !
07
1,
b1101 #
b1101 '
#254
02
17
b11101 !
06
1-
0,
b1110 #
b1110 '
#255
16
12
b11110 !
07
1,
b1111 #
b1111 '
#256
02
01
00
03
06
04
b0 !
05
1:
19
1<
1;
0-
0,
0/
0.
0)
0(
0+
0*
b0 #
b0 "
1$
b1 %
b0 &
b0 '
#257
13
14
10
15
11
16
b11111 !
17
12
1,
b1 #
b1 '
#258
16
b11110 !
07
02
1-
0,
b10 #
b10 '
#259
06
b11101 !
17
12
1,
b11 #
b11 '
#260
01
06
15
b11100 !
07
02
0-
0,
1.
b100 #
b100 '
#261
05
11
16
b11011 !
17
12
1,
b101 #
b101 '
#262
16
b11010 !
07
02
1-
0,
b110 #
b110 '
#263
06
b11001 !
17
12
1,
b111 #
b111 '
#264
00
01
06
14
05
b11000 !
07
02
0-
0,
1/
0.
b1000 #
b1000 '
#265
04
10
15
11
16
b10111 !
17
12
1,
b1001 #
b1001 '
#266
16
b10110 !
07
02
1-
0,
b1010 #
b1010 '
#267
06
b10101 !
17
12
1,
b1011 #
b1011 '
#268
01
06
15
b10100 !
07
02
0-
0,
1.
b1100 #
b1100 '
#269
05
11
16
b10011 !
17
12
1,
b1101 #
b1101 '
#270
16
b10010 !
07
02
1-
0,
b1110 #
b1110 '
#271
06
b10001 !
17
12
1,
b1111 #
b1111 '
#272
03
00
01
06
04
b1 !
05
02
09
0-
0,
0/
0.
1(
b0 #
b1 "
b1 &
b0 '
#273
b0 !
07
1,
b1 #
b1 '
#274
13
14
10
15
16
b11111 !
17
11
1-
0,
b10 #
b10 '
#275
b11110 !
07
1,
b11 #
b11 '
#276
15
06
b11101 !
17
01
0-
0,
1.
b100 #
b100 '
#277
b11100 !
07
1,
b101 #
b101 '
#278
05
16
b11011 !
17
11
1-
0,
b110 #
b110 '
#279
b11010 !
07
1,
b111 #
b111 '
#280
00
14
05
06
b11001 !
17
01
0-
0,
1/
0.
b1000 #
b1000 '
#281
b11000 !
07
1,
b1001 #
b1001 '
#282
04
10
15
16
b10111 !
17
11
1-
0,
b1010 #
b1010 '
#283
b10110 !
07
1,
b1011 #
b1011 '
#284
15
06
b10101 !
17
01
0-
0,
1.
b1100 #
b1100 '
#285
b10100 !
07
1,
b1101 #
b1101 '
#286
05
16
b10011 !
17
11
1-
0,
b1110 #
b1110 '
#287
b10010 !
07
1,
b1111 #
b1111 '
#288
03
00
04
b10 !
05
01
0:
19
0-
0,
0/
0.
1)
0(
b0 #
b10 "
b10 &
b0 '
#289
06
b1 !
17
12
1,
b1 #
b1 '
#290
03
04
00
05
07
02
b0 !
06
01
1-
0,
b10 #
b10 '
#291
13
14
10
15
11
16
b11111 !
17
12
1,
b11 #
b11 '
#292
15
07
02
b11110 !
16
01
0-
0,
1.
b100 #
b100 '
#293
06
b11101 !
17
12
1,
b101 #
b101 '
#294
15
07
02
b11100 !
06
01
1-
0,
b110 #
b110 '
#295
05
11
16
b11011 !
17
12
1,
b111 #
b111 '
#296
00
14
07
02
b11010 !
16
01
0-
0,
1/
0.
b1000 #
b1000 '
#297
06
b11001 !
17
12
1,
b1001 #
b1001 '
#298
14
00
05
07
02
b11000 !
06
01
1-
0,
b1010 #
b1010 '
#299
04
10
15
11
16
b10111 !
17
12
1,
b1011 #
b1011 '
#300
15
07
02
b10110 !
16
01
0-
0,
1.
b1100 #
b1100 '
#301
06
b10101 !
17
12
1,
b1101 #
b1101 '
#302
15
07
02
b10100 !
06
01
1-
0,
b1110 #
b1110 '
#303
05
11
16
b10011 !
17
12
1,
b1111 #
b1111 '
#304
03
00
04
02
b11 !
16
01
09
0-
0,
0/
0.
1(
b0 #
b11 "
b11 &
b0 '
#305
b10 !
07
1,
b1 #
b1 '
#306
06
b1 !
17
1-
0,
b10 #
b10 '
#307
b0 !
07
1,
b11 #
b11 '
#308
13
14
16
17
b11111 !
15
10
0-
0,
1.
b100 #
b100 '
#309
b11110 !
07
1,
b101 #
b101 '
#310
06
b11101 !
17
1-
0,
b110 #
b110 '
#311
b11100 !
07
1,
b111 #
b111 '
#312
14
16
17
b11011 !
05
00
0-
0,
1/
0.
b1000 #
b1000 '
#313
b11010 !
07
1,
b1001 #
b1001 '
#314
06
b11001 !
17
1-
0,
b1010 #
b1010 '
#315
b11000 !
07
1,
b1011 #
b1011 '
#316
04
16
17
b10111 !
15
10
0-
0,
1.
b1100 #
b1100 '
#317
b10110 !
07
1,
b1101 #
b1101 '
#318
06
b10101 !
17
1-
0,
b1110 #
b1110 '
#319
b10100 !
07
1,
b1111 #
b1111 '
#320
03
b100 !
04
00
1:
19
0;
0-
0,
0/
0.
0)
0(
1*
b0 #
b100 "
b100 &
b0 '
#321
05
11
16
b11 !
17
12
1,
b1 #
b1 '
#322
16
b10 !
07
02
1-
0,
b10 #
b10 '
#323
06
b1 !
17
12
1,
b11 #
b11 '
#324
01
03
06
04
07
02
b0 !
05
00
0-
0,
1.
b100 #
b100 '
#325
13
14
10
15
11
16
b11111 !
17
12
1,
b101 #
b101 '
#326
16
b11110 !
07
02
1-
0,
b110 #
b110 '
#327
06
b11101 !
17
12
1,
b111 #
b111 '
#328
01
06
07
02
b11100 !
15
00
0-
0,
1/
0.
b1000 #
b1000 '
#329
05
11
16
b11011 !
17
12
1,
b1001 #
b1001 '
#330
16
b11010 !
07
02
1-
0,
b1010 #
b1010 '
#331
06
b11001 !
17
12
1,
b1011 #
b1011 '
#332
01
14
06
07
02
b11000 !
05
00
0-
0,
1.
b1100 #
b1100 '
#333
04
10
15
11
16
b10111 !
17
12
1,
b1101 #
b1101 '
#334
16
b10110 !
07
02
1-
0,
b1110 #
b1110 '
#335
06
b10101 !
17
12
1,
b1111 #
b1111 '
#336
01
03
06
02
b101 !
15
00
09
0-
0,
0/
0.
1(
b0 #
b101 "
b101 &
b0 '
#337
b100 !
07
1,
b1 #
b1 '
#338
05
16
b11 !
17
11
1-
0,
b10 #
b10 '
#339
b10 !
07
1,
b11 #
b11 '
#340
03
04
06
17
01
b1 !
05
00
0-
0,
1.
b100 #
b100 '
#341
b0 !
07
1,
b101 #
b101 '
#342
13
14
10
15
16
b11111 !
17
11
1-
0,
b110 #
b110 '
#343
b11110 !
07
1,
b111 #
b111 '
#344
06
17
01
b11101 !
15
00
0-
0,
1/
0.
b1000 #
b1000 '
#345
b11100 !
07
1,
b1001 #
b1001 '
#346
05
16
b11011 !
17
11
1-
0,
b1010 #
b1010 '
#347
b11010 !
07
1,
b1011 #
b1011 '
#348
14
06
17
01
b11001 !
05
00
0-
0,
1.
b1100 #
b1100 '
#349
b11000 !
07
1,
b1101 #
b1101 '
#350
04
10
15
16
b10111 !
17
11
1-
0,
b1110 #
b1110 '
#351
b10110 !
07
1,
b1111 #
b1111 '
#352
03
01
b110 !
15
00
0:
19
0-
0,
0/
0.
1)
0(
b0 #
b110 "
b110 &
b0 '
#353
06
b101 !
17
12
1,
b1 #
b1 '
#354
15
07
02
b100 !
06
01
1-
0,
b10 #
b10 '
#355
05
11
16
b11 !
17
12
1,
b11 #
b11 '
#356
03
04
07
02
16
b10 !
05
01
00
0-
0,
1.
b100 #
b100 '
#357
06
b1 !
17
12
1,
b101 #
b101 '
#358
03
04
07
00
05
02
b0 !
06
01
1-
0,
b110 #
b110 '
#359
13
14
10
15
11
16
b11111 !
17
12
1,
b111 #
b111 '
