LAB_Sumador/Circuitos/Sumador/paralelladder.v
/*
 * Generated by Digital. Don't modify this file!
 * Any changes will be lost if this file is regenerated.
 */

module halfadder (
  input A,
  input B,
  output Co,
  output S
);
  assign S = (A ^ B);
  assign Co = (A & B);
endmodule

module fulladder (
  input A,
  input B,
  input Ci,
  output Co,
  output S
);
  wire s0;
  wire s1;
  wire s2;
  halfadder halfadder_i0 (
    .A( A ),
    .B( B ),
    .Co( s2 ),
    .S( s0 )
  );
  halfadder halfadder_i1 (
    .A( Ci ),
    .B( s0 ),
    .Co( s1 ),
    .S( S )
  );
  assign Co = (s2 | s1);
endmodule

module paralelladder (
  input a1,
  input b1,
  input a0,
  input b0,
  input a3,
  input b3,
  input a2,
  input b2,
  output s1,
  output s0,
  output s3,
  output s2,
  output s4
);
  wire s5;
  wire s6;
  wire s7;
  fulladder fulladder_i0 (
    .A( a0 ),
    .B( b0 ),
    .Ci( 1'b0 ),
    .Co( s5 ),
    .S( s0 )
  );
  fulladder fulladder_i1 (
    .A( a1 ),
    .B( b1 ),
    .Ci( s5 ),
    .Co( s6 ),
    .S( s1 )
  );
  fulladder fulladder_i2 (
    .A( a2 ),
    .B( b2 ),
    .Ci( s6 ),
    .Co( s7 ),
    .S( s2 )
  );
  fulladder fulladder_i3 (
    .A( a3 ),
    .B( b3 ),
    .Ci( s7 ),
    .Co( s4 ),
    .S( s3 )
  );
endmodule

LAB_Sumador/Circuitos/Sumador/paralelladder_tb.v
module testbech;

  // STIMULUS
  // reg a = 0, b = 0;
  // initial
  // begin
  //   # 17 a = 1, b = 1;
  //   # 11 a = 1, b = 0;
  //   # 29 a = 1, b = 1;
  //   # 11 a = 1, b = 0;
  //   # 100 $finish(); // [stop(), $finish()]
  // end

  reg [3:0] input_a;
  integer i;
  reg [3:0] input_b;
  integer o;
  initial
  begin
    for (i=0; i<16; i=i+1)
    begin         
		input_a = i;
		for (o=0; o<16; o=o+1)
		begin         
		  input_b = o;
		  #1;
		end
    end
  end

  // CLOCK STIMULUS
  // Make a regular pulsing clock.
  // reg clk = 0;
  // always #5 clk = !clk;

  /* // RESULT FOR DEVICE/DESIGN UNDER TEST */
  wire [4:0] outs;
  // DEVICE/DESIGN UNDER TEST
  paralelladder dut (
	.a3(input_a[3]), .a2(input_a[2]), .a1(input_a[1]), .a0(input_a[0]), 
	.b3(input_b[3]), .b2(input_b[2]), .b1(input_b[1]), .b0(input_b[0]), 
	.s4(outs[4]), .s3(outs[3]), .s2(outs[2]), .s1(outs[1]), .s0(outs[0])
  );

  /* // MONITOR */
  // initial
  //   $monitor("Time: %t, a = %d, b = %d => out = %d",
  //     $time, a, b, value);

  // WAVES IN VCD TO OPEN IN GTKWAVE
  initial
  begin
    $dumpfile("top.vcd");
    $dumpvars(0, testbech);
  end


endmodule

LAB_Sumador/Circuitos/Sumador/top.vcd
$date
	Wed Oct  4 05:27:46 2023
$end
$version
	Icarus Verilog
$end
$timescale
	1s
$end
$scope module testbech $end
$var wire 5 ! outs [4:0] $end
$var reg 4 " input_a [3:0] $end
$var reg 4 # input_b [3:0] $end
$var integer 32 $ i [31:0] $end
$var integer 32 % o [31:0] $end
$scope module dut $end
$var wire 1 & a0 $end
$var wire 1 ' a1 $end
$var wire 1 ( a2 $end
$var wire 1 ) a3 $end
$var wire 1 * b0 $end
$var wire 1 + b1 $end
$var wire 1 , b2 $end
$var wire 1 - b3 $end
$var wire 1 . s7 $end
$var wire 1 / s6 $end
$var wire 1 0 s5 $end
$var wire 1 1 s4 $end
$var wire 1 2 s3 $end
$var wire 1 3 s2 $end
$var wire 1 4 s1 $end
$var wire 1 5 s0 $end
$scope module fulladder_i0 $end
$var wire 1 & A $end
$var wire 1 * B $end
$var wire 1 6 Ci $end
$var wire 1 0 Co $end
$var wire 1 7 s2 $end
$var wire 1 8 s1 $end
$var wire 1 9 s0 $end
$var wire 1 5 S $end
$scope module halfadder_i0 $end
$var wire 1 & A $end
$var wire 1 * B $end
$var wire 1 7 Co $end
$var wire 1 9 S $end
$upscope $end
$scope module halfadder_i1 $end
$var wire 1 6 A $end
$var wire 1 9 B $end
$var wire 1 8 Co $end
$var wire 1 5 S $end
$upscope $end
$upscope $end
$scope module fulladder_i1 $end
$var wire 1 ' A $end
$var wire 1 + B $end
$var wire 1 0 Ci $end
$var wire 1 / Co $end
$var wire 1 : s2 $end
$var wire 1 ; s1 $end
$var wire 1 < s0 $end
$var wire 1 4 S $end
$scope module halfadder_i0 $end
$var wire 1 ' A $end
$var wire 1 + B $end
$var wire 1 : Co $end
$var wire 1 < S $end
$upscope $end
$scope module halfadder_i1 $end
$var wire 1 0 A $end
$var wire 1 < B $end
$var wire 1 ; Co $end
$var wire 1 4 S $end
$upscope $end
$upscope $end
$scope module fulladder_i2 $end
$var wire 1 ( A $end
$var wire 1 , B $end
$var wire 1 / Ci $end
$var wire 1 . Co $end
$var wire 1 = s2 $end
$var wire 1 > s1 $end
$var wire 1 ? s0 $end
$var wire 1 3 S $end
$scope module halfadder_i0 $end
$var wire 1 ( A $end
$var wire 1 , B $end
$var wire 1 = Co $end
$var wire 1 ? S $end
$upscope $end
$scope module halfadder_i1 $end
$var wire 1 / A $end
$var wire 1 ? B $end
$var wire 1 > Co $end
$var wire 1 3 S $end
$upscope $end
$upscope $end
$scope module fulladder_i3 $end
$var wire 1 ) A $end
$var wire 1 - B $end
$var wire 1 . Ci $end
$var wire 1 1 Co $end
$var wire 1 @ s2 $end
$var wire 1 A s1 $end
$var wire 1 B s0 $end
$var wire 1 2 S $end
$scope module halfadder_i0 $end
$var wire 1 ) A $end
$var wire 1 - B $end
$var wire 1 @ Co $end
$var wire 1 B S $end
$upscope $end
$scope module halfadder_i1 $end
$var wire 1 . A $end
$var wire 1 B B $end
$var wire 1 A Co $end
$var wire 1 2 S $end
$upscope $end
$upscope $end
$upscope $end
$upscope $end
$enddefinitions $end
#0
$dumpvars
0B
0A
0@
0?
0>
0=
0<
0;
0:
09
08
07
06
05
04
03
02
01
00
0/
0.
0-
0,
0+
0*
0)
0(
0'
0&
b0 %
b0 $
b0 #
b0 "
b0 !
$end
#1
b1 !
15
19
1*
b1 #
b1 %
#2
14
b10 !
05
1<
09
1+
0*
b10 #
b10 %
#3
b11 !
15
19
1*
b11 #
b11 %
#4
04
05
b100 !
13
0<
09
1?
0+
0*
1,
b100 #
b100 %
#5
b101 !
15
19
1*
b101 #
b101 %
#6
14
b110 !
05
1<
09
1+
0*
b110 #
b110 %
#7
b111 !
15
19
1*
b111 #
b111 %
#8
04
05
12
b1000 !
03
0<
09
1B
0?
0+
0*
1-
0,
b1000 #
b1000 %
#9
b1001 !
15
19
1*
b1001 #
b1001 %
#10
14
b1010 !
05
1<
09
1+
0*
b1010 #
b1010 %
#11
b1011 !
15
19
1*
b1011 #
b1011 %
#12
04
05
b1100 !
13
0<
09
1?
0+
0*
1,
b1100 #
b1100 %
#13
b1101 !
15
19
1*
b1101 #
b1101 %
#14
14
b1110 !
05
1<
09
1+
0*
b1110 #
b1110 %
#15
b1111 !
15
19
1*
b1111 #
b1111 %
#16
04
02
b1 !
03
0<
0B
0?
0+
0*
0-
0,
1&
b0 #
b1 "
b1 $
b0 %
#17
14
b10 !
05
10
09
17
1*
b1 #
b1 %
#18
b11 !
15
00
1<
19
07
1+
0*
b10 #
b10 %
#19
13
1/
04
1;
b100 !
05
10
09
17
1*
b11 #
b11 %
#20
02
0/
0.
0;
15
00
b101 !
13
0>
0<
19
07
1?
0+
0*
1,
b100 #
b100 %
#21
14
b110 !
05
10
09
17
1*
b101 #
b101 %
#22
b111 !
15
00
1<
19
07
1+
0*
b110 #
b110 %
#23
12
1.
03
1>
1/
04
1;
b1000 !
05
10
09
17
1*
b111 #
b111 %
#24
0/
01
0.
0;
15
00
12
0A
b1001 !
03
0>
0<
19
07
1B
0?
0+
0*
1-
0,
b1000 #
b1000 %
#25
14
b1010 !
05
10
09
17
1*
b1001 #
b1001 %
#26
b1011 !
15
00
1<
19
07
1+
0*
b1010 #
b1010 %
#27
13
1/
04
1;
b1100 !
05
10
09
17
1*
b1011 #
b1011 %
#28
01
12
0A
0/
0.
0;
15
00
b1101 !
13
0>
0<
19
07
1?
0+
0*
1,
b1100 #
b1100 %
#29
14
b1110 !
05
10
09
17
1*
b1101 #
b1101 %
#30
b1111 !
15
00
1<
19
07
1+
0*
b1110 #
b1110 %
#31
11
02
1A
1.
03
1>
1/
04
1;
b10000 !
05
10
09
17
1*
b1111 #
b1111 %
#32
0/
01
0.
14
0;
02
0A
b10 !
03
0>
00
0B
0?
07
0+
0*
0-
0,
1'
0&
b0 #
b10 "
b10 $
b0 %
#33
b11 !
15
19
1*
b1 #
b1 %
#34
13
04
1/
b100 !
05
0<
1:
09
1+
0*
b10 #
b10 %
#35
b101 !
15
19
1*
b11 #
b11 %
#36
02
0.
14
0/
05
b110 !
13
0>
1<
0:
09
1?
0+
0*
1,
b100 #
b100 %
#37
b111 !
15
19
1*
b101 #
b101 %
#38
12
1.
03
1>
04
1/
b1000 !
05
0<
1:
09
1+
0*
b110 #
b110 %
#39
b1001 !
15
19
1*
b111 #
b111 %
#40
01
0.
14
0/
05
12
0A
b1010 !
03
0>
1<
0:
09
1B
0?
0+
0*
1-
0,
b1000 #
b1000 %
#41
b1011 !
15
19
1*
b1001 #
b1001 %
#42
13
04
1/
b1100 !
05
0<
1:
09
1+
0*
b1010 #
b1010 %
#43
b1101 !
15
19
1*
b1011 #
b1011 %
#44
01
12
0A
0.
14
0/
05
b1110 !
13
0>
1<
0:
09
1?
0+
0*
1,
b1100 #
b1100 %
#45
b1111 !
15
19
1*
b1101 #
b1101 %
#46
11
02
1A
1.
03
1>
04
1/
b10000 !
05
0<
1:
09
1+
0*
b1110 #
b1110 %
#47
b10001 !
15
19
1*
b1111 #
b1111 %
#48
01
0.
14
0/
02
0A
b11 !
03
0>
1<
0:
0B
0?
0+
0*
0-
0,
1&
b0 #
b11 "
b11 $
b0 %
#49
13
1/
04
1;
b100 !
05
10
09
17
1*
b1 #
b1 %
#50
0;
b101 !
15
00
0<
1:
19
07
1+
0*
b10 #
b10 %
#51
14
b110 !
05
10
09
17
1*
b11 #
b11 %
#52
02
0.
0/
15
00
b111 !
13
0>
1<
0:
19
07
1?
0+
0*
1,
b100 #
b100 %
#53
12
1.
03
1>
1/
04
1;
b1000 !
05
10
09
17
1*
b101 #
b101 %
#54
0;
b1001 !
15
00
0<
1:
19
07
1+
0*
b110 #
b110 %
#55
14
b1010 !
05
10
09
17
1*
b111 #
b111 %
#56
01
0.
0/
15
00
12
0A
b1011 !
03
0>
1<
0:
19
07
1B
0?
0+
0*
1-
0,
b1000 #
b1000 %
#57
13
1/
04
1;
b1100 !
05
10
09
17
1*
b1001 #
b1001 %
#58
0;
b1101 !
15
00
0<
1:
19
07
1+
0*
b1010 #
b1010 %
#59
14
b1110 !
05
10
09
17
1*
b1011 #
b1011 %
#60
01
12
0A
0.
0/
15
00
b1111 !
13
0>
1<
0:
19
07
1?
0+
0*
1,
b1100 #
b1100 %
#61
11
02
1A
1.
03
1>
1/
04
1;
b10000 !
05
10
09
17
1*
b1101 #
b1101 %
#62
0;
b10001 !
15
00
0<
1:
19
07
1+
0*
b1110 #
b1110 %
#63
14
b10010 !
05
10
09
17
1*
b1111 #
b1111 %
#64
0.
01
13
0>
04
b100 !
02
0A
0/
00
0B
0:
07
0+
0*
0-
0,
0'
0&
1(
b0 #
b100 "
b100 $
b0 %
#65
b101 !
15
19
1*
b1 #
b1 %
#66
14
b110 !
05
1<
09
1+
0*
b10 #
b10 %
#67
b111 !
15
19
1*
b11 #
b11 %
#68
12
04
05
b1000 !
03
1.
0<
09
0?
1=
0+
0*
1,
b100 #
b100 %
#69
b1001 !
15
19
1*
b101 #
b101 %
#70
14
b1010 !
05
1<
09
1+
0*
b110 #
b110 %
#71
b1011 !
15
19
1*
b111 #
b111 %
#72
04
05
b1100 !
13
0.
0<
09
1B
1?
0=
0+
0*
1-
0,
b1000 #
b1000 %
#73
b1101 !
15
19
1*
b1001 #
b1001 %
#74
14
b1110 !
05
1<
09
1+
0*
b1010 #
b1010 %
#75
b1111 !
15
19
1*
b1011 #
b1011 %
#76
11
02
1A
04
05
b10000 !
03
1.
0<
09
0?
1=
0+
0*
1,
b1100 #
b1100 %
#77
b10001 !
15
19
1*
b1101 #
b1101 %
#78
14
b10010 !
05
1<
09
1+
0*
b1110 #
b1110 %
#79
b10011 !
15
19
1*
b1111 #
b1111 %
#80
01
04
0A
b101 !
13
0.
0<
0B
1?
0=
0+
0*
0-
0,
1&
b0 #
b101 "
b101 $
b0 %
#81
14
b110 !
05
10
09
17
1*
b1 #
b1 %
#82
b111 !
15
00
1<
19
07
1+
0*
b10 #
b10 %
#83
12
1.
03
1>
1/
04
1;
b1000 !
05
10
09
17
1*
b11 #
b11 %
#84
0/
0;
15
00
b1001 !
03
0>
0<
19
07
0?
1=
0+
0*
1,
b100 #
b100 %
#85
14
b1010 !
05
10
09
17
1*
b101 #
b101 %
#86
b1011 !
15
00
1<
19
07
1+
0*
b110 #
b110 %
#87
13
1/
04
1;
b1100 !
05
10
09
17
1*
b111 #
b111 %
#88
01
12
0A
0/
0;
15
00
b1101 !
13
0>
0.
0<
19
07
1B
1?
0=
0+
0*
1-
0,
b1000 #
b1000 %
#89
14
b1110 !
05
10
09
17
1*
b1001 #
b1001 %
#90
b1111 !
15
00
1<
19
07
1+
0*
b1010 #
b1010 %
#91
11
02
1A
1.
03
1>
1/
04
1;
b10000 !
05
10
09
17
1*
b1011 #
b1011 %
#92
0/
0;
15
00
b10001 !
03
0>
0<
19
07
0?
1=
0+
0*
1,
b1100 #
b1100 %
#93
14
b10010 !
05
10
09
17
1*
b1101 #
b1101 %
#94
b10011 !
15
00
1<
19
07
1+
0*
b1110 #
b1110 %
#95
13
1/
04
1;
b10100 !
05
10
09
17
1*
b1111 #
b1111 %
#96
02
0/
01
14
0;
0A
b110 !
13
0>
0.
00
0B
1?
0=
07
0+
0*
0-
0,
1'
0&
b0 #
b110 "
b110 $
b0 %
#97
b111 !
15
19
1*
b1 #
b1 %
#98
12
1.
03
1>
04
1/
b1000 !
05
0<
1:
09
1+
0*
b10 #
b10 %
#99
b1001 !
15
19
1*
b11 #
b11 %
#100
14
0/
05
b1010 !
03
0>
1<
0:
09
0?
1=
0+
0*
1,
b100 #
b100 %
#101
b1011 !
15
19
1*
b101 #
b101 %
#102
13
04
1/
b1100 !
05
0<
1:
09
1+
0*
b110 #
b110 %
#103
b1101 !
15
19
1*
b111 #
b111 %
#104
01
12
0A
14
0/
05
b1110 !
13
0>
0.
1<
0:
09
1B
1?
0=
0+
0*
1-
0,
b1000 #
b1000 %
#105
b1111 !
15
19
1*
b1001 #
b1001 %
#106
11
02
1A
1.
03
1>
04
1/
b10000 !
05
0<
1:
09
1+
0*
b1010 #
b1010 %
#107
b10001 !
15
19
1*
b1011 #
b1011 %
#108
14
0/
05
b10010 !
03
0>
1<
0:
09
0?
1=
0+
0*
1,
b1100 #
b1100 %
#109
b10011 !
15
19
1*
b1101 #
b1101 %
#110
13
04
1/
b10100 !
05
0<
1:
09
1+
0*
b1110 #
b1110 %
#111
b10101 !
15
19
1*
b1111 #
b1111 %
#112
02
01
14
0/
0A
b111 !
13
0>
0.
1<
0:
0B
1?
0=
0+
0*
0-
0,
1&
b0 #
b111 "
b111 $
b0 %
#113
12
1.
03
1>
1/
04
1;
b1000 !
05
10
09
17
1*
b1 #
b1 %
#114
0;
b1001 !
15
00
0<
1:
19
07
1+
0*
b10 #
b10 %
#115
14
b1010 !
05
10
09
17
1*
b11 #
b11 %
#116
0/
15
00
b1011 !
03
0>
1<
0:
19
07
0?
1=
0+
0*
1,
b100 #
b100 %
#117
13
1/
04
1;
b1100 !
05
10
09
17
1*
b101 #
b101 %
#118
0;
b1101 !
15
00
0<
1:
19
07
1+
0*
b110 #
b110 %
#119
14
b1110 !
05
10
09
17
1*
b111 #
b111 %
#120
01
12
0A
0/
15
00
b1111 !
13
0>
0.
1<
0:
19
07
1B
1?
0=
0+
0*
1-
0,
b1000 #
b1000 %
#121
11
02
1A
1.
03
1>
1/
04
1;
b10000 !
05
10
09
17
1*
b1001 #
b1001 %
#122
0;
b10001 !
15
00
0<
1:
19
07
1+
0*
b1010 #
b1010 %
#123
14
b10010 !
05
10
09
17
1*
b1011 #
b1011 %
#124
0/
15
00
b10011 !
03
0>
1<
0:
19
07
0?
1=
0+
0*
1,
b1100 #
b1100 %
#125
13
1/
04
1;
b10100 !
05
10
09
17
1*
b1101 #
b1101 %
#126
0;
b10101 !
15
00
0<
1:
19
07
1+
0*
b1110 #
b1110 %
#127
14
b10110 !
05
10
09
17
1*
b1111 #
b1111 %
#128
01
03
04
b1000 !
12
0A
0/
00
0.
0:
07
0=
0+
0*
0-
0,
0'
0&
1)
0(
b0 #
b1000 "
b1000 $
b0 %
#129
b1001 !
15
19
1*
b1 #
b1 %
#130
14
b1010 !
05
1<
09
1+
0*
b10 #
b10 %
#131
b1011 !
15
19
1*
b11 #
b11 %
#132
04
05
b1100 !
13
0<
09
1?
0+
0*
1,
b100 #
b100 %
#133
b1101 !
15
19
1*
b101 #
b101 %
#134
14
b1110 !
05
1<
09
1+
0*
b110 #
b110 %
#135
b1111 !
15
19
1*
b111 #
b111 %
#136
04
05
02
11
b10000 !
03
0<
09
0B
1@
0?
0+
0*
1-
0,
b1000 #
b1000 %
#137
b10001 !
15
19
1*
b1001 #
b1001 %
#138
14
b10010 !
05
1<
09
1+
0*
b1010 #
b1010 %
#139
b10011 !
15
19
1*
b1011 #
b1011 %
#140
04
05
b10100 !
13
0<
09
1?
0+
0*
1,
b1100 #
b1100 %
#141
b10101 !
15
19
1*
b1101 #
b1101 %
#142
14
b10110 !
05
1<
09
1+
0*
b1110 #
b1110 %
#143
b10111 !
15
19
1*
b1111 #
b1111 %
#144
04
12
01
b1001 !
03
0<
1B
0@
0?
0+
0*
0-
0,
1&
b0 #
b1001 "
b1001 $
b0 %
#145
14
b1010 !
05
10
09
17
1*
b1 #
b1 %
#146
b1011 !
15
00
1<
19
07
1+
0*
b10 #
b10 %
#147
13
1/
04
1;
b1100 !
05
10
09
17
1*
b11 #
b11 %
#148
01
12
0A
0/
0.
0;
15
00
b1101 !
13
0>
0<
19
07
1?
0+
0*
1,
b100 #
b100 %
#149
14
b1110 !
05
10
09
17
1*
b101 #
b101 %
#150
b1111 !
15
00
1<
19
07
1+
0*
b110 #
b110 %
#151
11
02
1A
1.
03
1>
1/
04
1;
b10000 !
05
10
09
17
1*
b111 #
b111 %
#152
0/
0.
0;
15
00
02
0A
b10001 !
03
0>
0<
19
07
0B
1@
0?
0+
0*
1-
0,
b1000 #
b1000 %
#153
14
b10010 !
05
10
09
17
1*
b1001 #
b1001 %
#154
b10011 !
15
00
1<
19
07
1+
0*
b1010 #
b1010 %
#155
13
1/
04
1;
b10100 !
05
10
09
17
1*
b1011 #
b1011 %
#156
02
0/
0.
0;
15
00
b10101 !
13
0>
0<
19
07
1?
0+
0*
1,
b1100 #
b1100 %
#157
14
b10110 !
05
10
09
17
1*
b1101 #
b1101 %
#158
b10111 !
15
00
1<
19
07
1+
0*
b1110 #
b1110 %
#159
12
1.
03
1>
1/
04
1;
b11000 !
05
10
09
17
1*
b1111 #
b1111 %
#160
0/
0.
14
0;
12
0A
01
b1010 !
03
0>
00
1B
0@
0?
07
0+
0*
0-
0,
1'
0&
b0 #
b1010 "
b1010 $
b0 %
#161
b1011 !
15
19
1*
b1 #
b1 %
#162
13
04
1/
b1100 !
05
0<
1:
09
1+
0*
b10 #
b10 %
#163
b1101 !
15
19
1*
b11 #
b11 %
#164
01
12
0A
0.
14
0/
05
b1110 !
13
0>
1<
0:
09
1?
0+
0*
1,
b100 #
b100 %
#165
b1111 !
15
19
1*
b101 #
b101 %
#166
11
02
1A
1.
03
1>
04
1/
b10000 !
05
0<
1:
09
1+
0*
b110 #
b110 %
#167
b10001 !
15
19
1*
b111 #
b111 %
#168
0.
14
0/
05
02
0A
b10010 !
03
0>
1<
0:
09
0B
1@
0?
0+
0*
1-
0,
b1000 #
b1000 %
#169
b10011 !
15
19
1*
b1001 #
b1001 %
#170
13
04
1/
b10100 !
05
0<
1:
09
1+
0*
b1010 #
b1010 %
#171
b10101 !
15
19
1*
b1011 #
b1011 %
#172
02
0.
14
0/
05
b10110 !
13
0>
1<
0:
09
1?
0+
0*
1,
b1100 #
b1100 %
#173
b10111 !
15
19
1*
b1101 #
b1101 %
#174
12
1.
03
1>
04
1/
b11000 !
05
0<
1:
09
1+
0*
b1110 #
b1110 %
#175
b11001 !
15
19
1*
b1111 #
b1111 %
#176
0.
14
0/
12
0A
01
b1011 !
03
0>
1<
0:
1B
0@
0?
0+
0*
0-
0,
1&
b0 #
b1011 "
b1011 $
b0 %
#177
13
1/
04
1;
b1100 !
05
10
09
17
1*
b1 #
b1 %
#178
0;
b1101 !
15
00
0<
1:
19
07
1+
0*
b10 #
b10 %
#179
14
b1110 !
05
10
09
17
1*
b11 #
b11 %
#180
01
12
0A
0.
0/
15
00
b1111 !
13
0>
1<
0:
19
07
1?
0+
0*
1,
b100 #
b100 %
#181
11
02
1A
1.
03
1>
1/
04
1;
b10000 !
05
10
09
17
1*
b101 #
b101 %
#182
0;
b10001 !
15
00
0<
1:
19
07
1+
0*
b110 #
b110 %
#183
14
b10010 !
05
10
09
17
1*
b111 #
b111 %
#184
0.
0/
15
00
02
0A
b10011 !
03
0>
1<
0:
19
07
0B
1@
0?
0+
0*
1-
0,
b1000 #
b1000 %
#185
13
1/
04
1;
b10100 !
05
10
09
17
1*
b1001 #
b1001 %
#186
0;
b10101 !
15
00
0<
1:
19
07
1+
0*
b1010 #
b1010 %
#187
14
b10110 !
05
10
09
17
1*
b1011 #
b1011 %
#188
02
0.
0/
15
00
b10111 !
13
0>
1<
0:
19
07
1?
0+
0*
1,
b1100 #
b1100 %
#189
12
1.
03
1>
1/
04
1;
b11000 !
05
10
09
17
1*
b1101 #
b1101 %
#190
0;
b11001 !
15
00
0<
1:
19
07
1+
0*
b1110 #
b1110 %
#191
14
b11010 !
05
10
09
17
1*
b1111 #
b1111 %
#192
0.
13
0>
04
12
0A
b1100 !
01
0/
00
1B
0@
0:
07
0+
0*
0-
0,
0'
0&
1(
b0 #
b1100 "
b1100 $
b0 %
#193
b1101 !
15
19
1*
b1 #
b1 %
#194
14
b1110 !
05
1<
09
1+
0*
b10 #
b10 %
#195
b1111 !
15
19
1*
b11 #
b11 %
#196
11
02
1A
04
05
b10000 !
03
1.
0<
09
0?
1=
0+
0*
1,
b100 #
b100 %
#197
b10001 !
15
19
1*
b101 #
b101 %
#198
14
b10010 !
05
1<
09
1+
0*
b110 #
b110 %
#199
b10011 !
15
19
1*
b111 #
b111 %
#200
04
05
0A
b10100 !
13
0.
0<
09
0B
1@
1?
0=
0+
0*
1-
0,
b1000 #
b1000 %
#201
b10101 !
15
19
1*
b1001 #
b1001 %
#202
14
b10110 !
05
1<
09
1+
0*
b1010 #
b1010 %
#203
b10111 !
15
19
1*
b1011 #
b1011 %
#204
12
04
05
b11000 !
03
1.
0<
09
0?
1=
0+
0*
1,
b1100 #
b1100 %
#205
b11001 !
15
19
1*
b1101 #
b1101 %
#206
14
b11010 !
05
1<
09
1+
0*
b1110 #
b1110 %
#207
b11011 !
15
19
1*
b1111 #
b1111 %
#208
04
01
b1101 !
13
0.
0<
1B
0@
1?
0=
0+
0*
0-
0,
1&
b0 #
b1101 "
b1101 $
b0 %
#209
14
b1110 !
05
10
09
17
1*
b1 #
b1 %
#210
b1111 !
15
00
1<
19
07
1+
0*
b10 #
b10 %
#211
11
02
1A
1.
03
1>
1/
04
1;
b10000 !
05
10
09
17
1*
b11 #
b11 %
#212
0/
0;
15
00
b10001 !
03
0>
0<
19
07
0?
1=
0+
0*
1,
b100 #
b100 %
#213
14
b10010 !
05
10
09
17
1*
b101 #
b101 %
#214
b10011 !
15
00
1<
19
07
1+
0*
b110 #
b110 %
#215
13
1/
04
1;
b10100 !
05
10
09
17
1*
b111 #
b111 %
#216
02
0/
0;
15
00
0A
b10101 !
13
0>
0.
0<
19
07
0B
1@
1?
0=
0+
0*
1-
0,
b1000 #
b1000 %
#217
14
b10110 !
05
10
09
17
1*
b1001 #
b1001 %
#218
b10111 !
15
00
1<
19
07
1+
0*
b1010 #
b1010 %
#219
12
1.
03
1>
1/
04
1;
b11000 !
05
10
09
17
1*
b1011 #
b1011 %
#220
0/
0;
15
00
b11001 !
03
0>
0<
19
07
0?
1=
0+
0*
1,
b1100 #
b1100 %
#221
14
b11010 !
05
10
09
17
1*
b1101 #
b1101 %
#222
b11011 !
15
00
1<
19
07
1+
0*
b1110 #
b1110 %
#223
13
1/
04
1;
b11100 !
05
10
09
17
1*
b1111 #
b1111 %
#224
12
0A
0/
14
0;
01
b1110 !
13
0>
0.
00
1B
0@
1?
0=
07
0+
0*
0-
0,
1'
0&
b0 #
b1110 "
b1110 $
b0 %
#225
b1111 !
15
19
1*
b1 #
b1 %
#226
11
02
1A
1.
03
1>
04
1/
b10000 !
05
0<
1:
09
1+
0*
b10 #
b10 %
#227
b10001 !
15
19
1*
b11 #
b11 %
#228
14
0/
05
b10010 !
03
0>
1<
0:
09
0?
1=
0+
0*
1,
b100 #
b100 %
#229
b10011 !
15
19
1*
b101 #
b101 %
#230
13
04
1/
b10100 !
05
0<
1:
09
1+
0*
b110 #
b110 %
#231
b10101 !
15
19
1*
b111 #
b111 %
#232
02
14
0/
05
0A
b10110 !
13
0>
0.
1<
0:
09
0B
1@
1?
0=
0+
0*
1-
0,
b1000 #
b1000 %
#233
b10111 !
15
19
1*
b1001 #
b1001 %
#234
12
1.
03
1>
04
1/
b11000 !
05
0<
1:
09
1+
0*
b1010 #
b1010 %
#235
b11001 !
15
19
1*
b1011 #
b1011 %
#236
14
0/
05
b11010 !
03
0>
1<
0:
09
0?
1=
0+
0*
1,
b1100 #
b1100 %
#237
b11011 !
15
19
1*
b1101 #
b1101 %
#238
13
04
1/
b11100 !
05
0<
1:
09
1+
0*
b1110 #
b1110 %
#239
b11101 !
15
19
1*
b1111 #
b1111 %
#240
12
0A
14
0/
01
b1111 !
13
0>
0.
1<
0:
1B
0@
1?
0=
0+
0*
0-
0,
1&
b0 #
b1111 "
b1111 $
b0 %
#241
11
02
1A
1.
03
1>
1/
04
1;
b10000 !
05
10
09
17
1*
b1 #
b1 %
#242
0;
b10001 !
15
00
0<
1:
19
07
1+
0*
b10 #
b10 %
#243
14
b10010 !
05
10
09
17
1*
b11 #
b11 %
#244
0/
15
00
b10011 !
03
0>
1<
0:
19
07
0?
1=
0+
0*
1,
b100 #
b100 %
#245
13
1/
04
1;
b10100 !
05
10
09
17
1*
b101 #
b101 %
#246
0;
b10101 !
15
00
0<
1:
19
07
1+
0*
b110 #
b110 %
#247
14
b10110 !
05
10
09
17
1*
b111 #
b111 %
#248
02
0/
15
00
0A
b10111 !
13
0>
0.
1<
0:
19
07
0B
1@
1?
0=
0+
0*
1-
0,
b1000 #
b1000 %
#249
12
1.
03
1>
1/
04
1;
b11000 !
05
10
09
17
1*
b1001 #
b1001 %
#250
0;
b11001 !
15
00
0<
1:
19
07
1+
0*
b1010 #
b1010 %
#251
14
b11010 !
05
10
09
17
1*
b1011 #
b1011 %
#252
0/
15
00
b11011 !
03
0>
1<
0:
19
07
0?
1=
0+
0*
1,
b1100 #
b1100 %
#253
13
1/
04
1;
b11100 !
05
10
09
17
1*
b1101 #
b1101 %
#254
0;
b11101 !
15
00
0<
1:
19
07
1+
0*
b1110 #
b1110 %
#255
14
b11110 !
05
10
09
17
1*
b1111 #
b1111 %
#256
b10000 $
b10000 %
